djangoprime/__init__.py
djangoprime/config.py
djangoprime/admin/actions/__init__.py
djangoprime/admin/actions/status.py
djangoprime/core/__init__.py
djangoprime/core/base.py
djangoprime/core/exception.py
djangoprime/enum/__init__.py
djangoprime/enum/auth.py
djangoprime/enum/crud.py
djangoprime/enum/database.py
djangoprime/enum/mail.py
djangoprime/enum/media.py
djangoprime/enum/models.py
djangoprime/enum/permissions.py
djangoprime/enum/response.py
djangoprime/enum/throttling.py
djangoprime/enum/token.py
djangoprime/exceptions/__init__.py
djangoprime/exceptions/authentication.py
djangoprime/exceptions/common.py
djangoprime/exceptions/password.py
djangoprime/exceptions/throttling.py
djangoprime/exceptions/token.py
djangoprime/exceptions/handler/__init__.py
djangoprime/exceptions/handler/exception_handler.py
djangoprime/helpers/__init__.py
djangoprime/helpers/common.py
djangoprime/helpers/data_units.py
djangoprime/helpers/date_and_time.py
djangoprime/helpers/html.py
djangoprime/helpers/slugify.py
djangoprime/middleware/__init__.py
djangoprime/middleware/api_response.py
djangoprime/middleware/authentication/JWTAuthentication.py
djangoprime/middleware/authentication/__init__.py
djangoprime/models/__init__.py
djangoprime/models/abstract/seo/__init__.py
djangoprime/models/abstract/seo/base.py
djangoprime/models/abstract/seo/open_graph.py
djangoprime/models/abstract/seo/twitter_card.py
djangoprime/models/choices/choice.py
djangoprime/models/choices/seo.py
djangoprime/models/choices/text_choices.py
djangoprime/response/__init__.py
djangoprime/response/api_respose.py
djangoprime/serializers/__init__.py
djangoprime/validators/__init__.py
djangoprime/validators/common.py
djangoprime/validators/file.py
djangoprime/validators/image.py
djangoprime/validators/operations.py
djangoprime/validators/seo.py
djangoprime-0.0.3.dist-info/LICENSE
djangoprime-0.0.3.dist-info/METADATA
djangoprime-0.0.3.dist-info/WHEEL
djangoprime-0.0.3.dist-info/top_level.txt
djangoprime-0.0.3.dist-info/RECORD
