Metadata-Version: 2.2
Name: djangoprime
Version: 0.0.3
Summary: DjangoPrime is an all-in-one Django library designed to accelerate your development process. It offers over 1000 custom exception classes, a powerful suite of middleware integrations, flexible JWT configuration services, and advanced tools for managing enums and models. DjangoPrime also includes pre-built solutions, absolute models, and modular components that allow developers to build scalable, maintainable, and sophisticated Django applications easily.
Author-email: Ankaj Gupta <ankajgupta02@gmail.com>, Coder Website <contact@coderwebsite.com>
License: MIT
Keywords: django,djangoprime,django-prime,django project setup,django jwt,django custom response,django projects,django modular components
Classifier: Development Status :: 4 - Beta
Classifier: Environment :: Web Environment
Classifier: Framework :: Django
Classifier: Intended Audience :: Developers
Classifier: License :: OSI Approved :: MIT License
Classifier: Operating System :: OS Independent
Classifier: Programming Language :: Python
Classifier: Programming Language :: Python :: 3.11
Classifier: Programming Language :: Python :: 3.12
Classifier: Programming Language :: Python :: 3.13
Classifier: Topic :: Internet :: WWW/HTTP
Requires-Python: >=3.11
License-File: LICENSE
Requires-Dist: requests
Requires-Dist: unidecode
Requires-Dist: django
Requires-Dist: djangorestframework
Requires-Dist: pygments
Requires-Dist: djangorestframework-simplejwt
